doxa_cli/__init__.py
doxa_cli/__main__.py
doxa_cli/config.py
doxa_cli/constants.py
doxa_cli/errors.py
doxa_cli/utils.py
doxa_cli/commands/config.py
doxa_cli/commands/login.py
doxa_cli/commands/logout.py
doxa_cli/commands/surprise.py
doxa_cli/commands/upload.py
doxa_cli/commands/user.py
doxa_cli/commands/version.py
doxa_cli-0.1.8.dist-info/METADATA
doxa_cli-0.1.8.dist-info/WHEEL
doxa_cli-0.1.8.dist-info/entry_points.txt
doxa_cli-0.1.8.dist-info/licenses/LICENSE
doxa_cli-0.1.8.dist-info/RECORD
