Metadata-Version: 2.3
Name: doxa-cli
Version: 0.1.8
Summary: The CLI for interacting with DOXA, a powerful platform for running engaging online artificial intelligence competitions.
Project-URL: Homepage, https://github.com/DoxaAI/cli
Project-URL: Bug Tracker, https://github.com/DoxaAI/cli/issues
Author-email: Jeremy Lo Ying Ping <jeremy@doxaai.com>
License: MIT License
License-File: LICENSE
Classifier: License :: OSI Approved :: MIT License
Classifier: Operating System :: OS Independent
Classifier: Programming Language :: Python :: 3
Requires-Python: >=3.7
Requires-Dist: halo>=0.0.31,~=0.0.31
Requires-Dist: pyyaml>=6.0
Requires-Dist: requests-toolbelt~=0.10.1
Requires-Dist: requests~=2.26.0
Requires-Dist: typer[all]>=0.9.0
